pyOceanopticsSpectrometer/__init__.py
pyOceanopticsSpectrometer/config.json
pyOceanopticsSpectrometer/driver.py
pyOceanopticsSpectrometer/main.py
pyOceanopticsSpectrometer/plots.py
pyOceanopticsSpectrometer/graphics/ligthOFF.png
pyOceanopticsSpectrometer/graphics/ligthON.png
pyOceanopticsSpectrometer/graphics/pause.png
pyOceanopticsSpectrometer/graphics/play.png
pyOceanopticsSpectrometer/graphics/refresh.png
pyOceanopticsSpectrometer/graphics/stop.png
pyoceanopticsspectrometer-0.4.dist-info/METADATA
pyoceanopticsspectrometer-0.4.dist-info/WHEEL
pyoceanopticsspectrometer-0.4.dist-info/entry_points.txt
pyoceanopticsspectrometer-0.4.dist-info/top_level.txt
pyoceanopticsspectrometer-0.4.dist-info/RECORD
