Metadata-Version: 2.4
Name: pyOceanopticsSpectrometer
Version: 0.4
Summary: A python library/GUI to access and control OceanOptics spectrometers
Home-page: https://github.com/MicheleCotrufo/
Author: Michele Cotrufo
Author-email: michele.cotrufo@gmail.com
License: MIT
Requires-Dist: abstract_instrument_interface>=0.9
Requires-Dist: seabreeze
Requires-Dist: PyQt5>=5.15.6
Requires-Dist: pyqtgraph
Requires-Dist: pyvisa
Requires-Dist: numpy
Dynamic: author
Dynamic: author-email
Dynamic: description
Dynamic: description-content-type
Dynamic: home-page
Dynamic: license
Dynamic: requires-dist
Dynamic: summary
